chrononaut/__init__.py
chrononaut/change_info.py
chrononaut/context_managers.py
chrononaut/data_converters.py
chrononaut/exceptions.py
chrononaut/flask_versioning.py
chrononaut/history_mapper.py
chrononaut/models.py
chrononaut/unsafe.py
chrononaut/versioned.py
chrononaut-0.4.1.dist-info/LICENSE
chrononaut-0.4.1.dist-info/METADATA
chrononaut-0.4.1.dist-info/WHEEL
chrononaut-0.4.1.dist-info/top_level.txt
chrononaut-0.4.1.dist-info/RECORD
