Metadata-Version: 2.1
Name: chrononaut
Version: 0.4.1
Summary: UNKNOWN
Home-page: https://github.com/onecodex/chrononaut
Author: Nick Greenfield
Author-email: opensource@onecodex.com
License: MIT License
Keywords: Chrononaut
Platform: UNKNOWN
Classifier: License :: OSI Approved :: MIT License
Classifier: Intended Audience :: Developers
Classifier: Operating System :: OS Independent
Classifier: Topic :: Software Development :: Libraries :: Python Modules
Classifier: Topic :: Internet :: WWW/HTTP
Classifier: Framework :: Flask
Classifier: Programming Language :: Python
Classifier: Programming Language :: Python :: 3
Classifier: Programming Language :: Python :: 3.7
Classifier: Programming Language :: Python :: 3.8
Classifier: Programming Language :: Python :: 3.9
Classifier: Programming Language :: Python :: 3.10
License-File: LICENSE
Requires-Dist: Flask (>=2.1.0)
Requires-Dist: Flask-SQLAlchemy (>=2.5.1)
Requires-Dist: SQLAlchemy (>=1.4.0)
Requires-Dist: psycopg2 (>=2.7.1)
Provides-Extra: user_info
Requires-Dist: Flask-Login (>=0.4.0) ; extra == 'user_info'
